aimodel/Config.py
aimodel/__init__.py
aimodel/ddpg_ray.py
model/Config.py
model/__init__.py
model/ddpg_ray.py
aimodel-1.0.0.dist-info/METADATA
aimodel-1.0.0.dist-info/WHEEL
aimodel-1.0.0.dist-info/top_level.txt
aimodel-1.0.0.dist-info/RECORD
